zenoo_rpc/__init__.py
zenoo_rpc/client.py
zenoo_rpc/ai/__init__.py
zenoo_rpc/ai/core/ai_assistant.py
zenoo_rpc/ai/core/ai_client.py
zenoo_rpc/ai/diagnostics/__init__.py
zenoo_rpc/ai/diagnostics/error_analyzer.py
zenoo_rpc/ai/query/__init__.py
zenoo_rpc/ai/query/nl_to_query.py
zenoo_rpc/ai/query/query_optimizer.py
zenoo_rpc/batch/__init__.py
zenoo_rpc/batch/context.py
zenoo_rpc/batch/exceptions.py
zenoo_rpc/batch/executor.py
zenoo_rpc/batch/manager.py
zenoo_rpc/batch/operations.py
zenoo_rpc/cache/__init__.py
zenoo_rpc/cache/backends.py
zenoo_rpc/cache/decorators.py
zenoo_rpc/cache/exceptions.py
zenoo_rpc/cache/keys.py
zenoo_rpc/cache/manager.py
zenoo_rpc/cache/strategies.py
zenoo_rpc/exceptions/__init__.py
zenoo_rpc/exceptions/base.py
zenoo_rpc/exceptions/mapping.py
zenoo_rpc/mcp/__init__.py
zenoo_rpc/mcp/client.py
zenoo_rpc/mcp/exceptions.py
zenoo_rpc/mcp/integration.py
zenoo_rpc/mcp/manager.py
zenoo_rpc/mcp/transport.py
zenoo_rpc/mcp_server/__init__.py
zenoo_rpc/mcp_server/cli.py
zenoo_rpc/mcp_server/config.py
zenoo_rpc/mcp_server/exceptions.py
zenoo_rpc/mcp_server/security.py
zenoo_rpc/mcp_server/server.py
zenoo_rpc/models/__init__.py
zenoo_rpc/models/base.py
zenoo_rpc/models/common.py
zenoo_rpc/models/fields.py
zenoo_rpc/models/registry.py
zenoo_rpc/models/relationships.py
zenoo_rpc/query/__init__.py
zenoo_rpc/query/builder.py
zenoo_rpc/query/expressions.py
zenoo_rpc/query/filters.py
zenoo_rpc/query/lazy.py
zenoo_rpc/retry/__init__.py
zenoo_rpc/retry/decorators.py
zenoo_rpc/retry/exceptions.py
zenoo_rpc/retry/policies.py
zenoo_rpc/retry/strategies.py
zenoo_rpc/transaction/__init__.py
zenoo_rpc/transaction/context.py
zenoo_rpc/transaction/exceptions.py
zenoo_rpc/transaction/manager.py
zenoo_rpc/transport/__init__.py
zenoo_rpc/transport/httpx_transport.py
zenoo_rpc/transport/pool.py
zenoo_rpc/transport/session.py
zenoo_rpc/utils/fallback.py
zenoo_rpc-0.2.4.dist-info/licenses/LICENSE
zenoo_rpc-0.2.4.dist-info/METADATA
zenoo_rpc-0.2.4.dist-info/WHEEL
zenoo_rpc-0.2.4.dist-info/top_level.txt
zenoo_rpc-0.2.4.dist-info/RECORD
