Metadata-Version: 2.4
Name: zenoo-rpc
Version: 0.2.4
Summary: A zen-like, modern async Python library for Odoo RPC with type safety, transactions, caching, and AI-powered MCP integration
Author-email: Lê Anh Tuấn <justin.le.1105@gmail.com>
License: MIT
Project-URL: Homepage, https://github.com/tuanle96/zenoo-rpc
Project-URL: Documentation, https://zenoo-rpc.readthedocs.io
Project-URL: Repository, https://github.com/tuanle96/zenoo-rpc
Project-URL: Issues, https://github.com/tuanle96/zenoo-rpc/issues
Classifier: Development Status :: 3 - Alpha
Classifier: Intended Audience :: Developers
Classifier: License :: OSI Approved :: MIT License
Classifier: Programming Language :: Python :: 3
Classifier: Programming Language :: Python :: 3.8
Classifier: Programming Language :: Python :: 3.9
Classifier: Programming Language :: Python :: 3.10
Classifier: Programming Language :: Python :: 3.11
Classifier: Programming Language :: Python :: 3.12
Classifier: Framework :: AsyncIO
Classifier: Topic :: Software Development :: Libraries :: Python Modules
Classifier: Topic :: Office/Business :: Financial :: Accounting
Requires-Python: >=3.8
License-File: LICENSE
Requires-Dist: httpx>=0.25.0
Requires-Dist: h2>=4.0.0
Requires-Dist: pydantic>=2.0.0
Requires-Dist: typing-extensions>=4.0.0
Provides-Extra: dev
Requires-Dist: pytest>=7.0.0; extra == "dev"
Requires-Dist: pytest-asyncio>=0.21.0; extra == "dev"
Requires-Dist: pytest-cov>=4.0.0; extra == "dev"
Requires-Dist: codecov>=2.1.0; extra == "dev"
Requires-Dist: black>=23.0.0; extra == "dev"
Requires-Dist: ruff>=0.1.0; extra == "dev"
Requires-Dist: mypy>=1.0.0; extra == "dev"
Requires-Dist: pre-commit>=3.0.0; extra == "dev"
Provides-Extra: docs
Requires-Dist: mkdocs>=1.5.0; extra == "docs"
Requires-Dist: mkdocs-material>=9.0.0; extra == "docs"
Requires-Dist: mkdocstrings[python]>=0.23.0; extra == "docs"
Provides-Extra: redis
Requires-Dist: redis[hiredis]>=5.0.0; extra == "redis"
Provides-Extra: ai
Requires-Dist: litellm>=1.0.0; extra == "ai"
Provides-Extra: mcp
Requires-Dist: mcp>=1.0.0; extra == "mcp"
Requires-Dist: fastapi>=0.104.0; extra == "mcp"
Requires-Dist: uvicorn>=0.24.0; extra == "mcp"
Dynamic: license-file
